{"id": "bergisches-e-bike", "name": "Bergisches e-Bike", "location": {"latitude": 51.0192, "longitude": 7.18025, "city": "Bergisches e-Bike", "country": "DE"}, "href": "/v2/networks/bergisches-e-bike", "company": ["Nextbike GmbH"], "system": "Nextbike", "stations": [{"id": "09d182cbe44fe74e161566ac18b5207e", "name": "R\u00f6srath - Forsbach - Halfenhof", "latitude": 50.924389, "longitude": 7.17625, "timestamp": "2025-05-03T03:03:40.740850+00:00Z", "free_bikes": 6, "empty_slots": 0, "extra": {"uid": "32136249", "number": "51523", "slots": 6, "bike_uids": ["42687", "42653", "42628", "42605", "532036", "532006"], "virtual": false}}, {"id": "10679365865b0cce0148d50317baf908", "name": "Wermelskirchen Busbahnhof", "latitude": 51.144028, "longitude": 7.219444, "timestamp": "2025-05-03T03:03:40.740366+00:00Z", "free_bikes": 0, "empty_slots": 8, "extra": {"uid": "30240427", "number": "51528", "slots": 8, "bike_uids": [], "virtual": false}}, {"id": "1309b4cc4a5bda8cc7a0177f71bed72e", "name": "Ehrenmal-P\u00e4rkchen", "latitude": 51.13818, "longitude": 7.187954, "timestamp": "2025-05-03T03:03:40.741409+00:00Z", "free_bikes": 1, "empty_slots": null, "extra": {"uid": "476557459", "number": "51579", "bike_uids": ["532001"], "virtual": false}}, {"id": "14046f1cd4fbc78143460c43f4a566cf", "name": "Bhf St\u00fcmpen", "latitude": 50.898817, "longitude": 7.159052, "timestamp": "2025-05-03T03:03:40.740926+00:00Z", "free_bikes": 3, "empty_slots": null, "extra": {"uid": "49442145", "number": "51550", "bike_uids": ["42643", "532047", "532041"], "virtual": true}}, {"id": "1a185c6caa2a66ca2b2510b776b5daff", "name": "Opladen Busbahnhof - BERGISCHES", "latitude": 51.066681, "longitude": 7.006359, "timestamp": "2025-05-03T03:03:40.741028+00:00Z", "free_bikes": 0, "empty_slots": null, "extra": {"uid": "114158034", "number": "51556", "bike_uids": [], "virtual": false}}, {"id": "1f11852e954a42896af1c6f8c89dd6f1", "name": "Wermelskirchen Dabringhausen", "latitude": 51.092889, "longitude": 7.1875, "timestamp": "2025-05-03T03:03:40.740788+00:00Z", "free_bikes": 2, "empty_slots": 4, "extra": {"uid": "32135897", "number": "51534", "slots": 6, "bike_uids": ["42613", "532013"], "virtual": false}}, {"id": "228869b9b8ed5275f4a095faa848d614", "name": "R\u00f6srath - Hoffnungsthal, Rathaus", "latitude": 50.914278, "longitude": 7.196167, "timestamp": "2025-05-03T03:03:40.740833+00:00Z", "free_bikes": 0, "empty_slots": 5, "extra": {"uid": "32136150", "number": "51520", "slots": 6, "bike_uids": [], "virtual": false}}, {"id": "22bed1536a980c5cee887c36e3034bb7", "name": "Lohmar - Honrath Bahnhof - Bergisches", "latitude": 50.910218, "longitude": 7.251695, "timestamp": "2025-05-03T03:03:40.741092+00:00Z", "free_bikes": 0, "empty_slots": null, "extra": {"uid": "149965663", "number": "51559", "bike_uids": [], "virtual": false}}, {"id": "2409dbf0f168d43ee04bb646e6d989b3", "name": "Overath Marialinden", "latitude": 50.933167, "longitude": 7.325056, "timestamp": "2025-05-03T03:03:40.740775+00:00Z", "free_bikes": 0, "empty_slots": null, "extra": {"uid": "32135725", "number": "51536", "bike_uids": [], "virtual": true}}, {"id": "24991335f6cd8315debed0e8f338001f", "name": "Odenthal Voiswinkel", "latitude": 51.017056, "longitude": 7.123833, "timestamp": "2025-05-03T03:03:40.740745+00:00Z", "free_bikes": 0, "empty_slots": null, "extra": {"uid": "32135544", "number": "51544", "bike_uids": [], "virtual": true}}, {"id": "27294166fb6fb043896f8e217b1cdbf9", "name": "(H) Odenthaler Str. - Bergisches", "latitude": 51.001124, "longitude": 7.042472, "timestamp": "2025-05-03T03:03:40.741152+00:00Z", "free_bikes": 0, "empty_slots": null, "extra": {"uid": "149975040", "number": "51562", "bike_uids": [], "virtual": false}}, {"id": "33fad303276243ccf38a6f3a259104e3", "name": "R\u00f6srath Kleineichen", "latitude": 50.904417, "longitude": 7.147167, "timestamp": "2025-05-03T03:03:40.740973+00:00Z", "free_bikes": 0, "empty_slots": null, "extra": {"uid": "81377215", "number": "51553", "bike_uids": [], "virtual": true}}, {"id": "3e8e58e71d40ea9f9aabaf54e46629d5", "name": "Odenthal Herzogenfeld", "latitude": 51.031841, "longitude": 7.117236, "timestamp": "2025-05-03T03:03:40.740405+00:00Z", "free_bikes": 2, "empty_slots": 8, "extra": {"uid": "30282744", "number": "51532", "slots": 8, "bike_uids": ["42678", "532015"], "virtual": false}}, {"id": "447841f4c4f469cb57e9ea97e7d45a69", "name": "Gronau \u2013 Heidkamper Stra\u00dfe", "latitude": 50.984328, "longitude": 7.126362, "timestamp": "2025-05-03T03:03:40.741267+00:00Z", "free_bikes": 1, "empty_slots": null, "extra": {"uid": "227530569", "number": "51567", "bike_uids": ["42627"], "virtual": false}}, {"id": "4a57fd863d64fd1f9e699e0d35b90ee0", "name": "Gl\u00f6busch Haltestelle \u201eSch\u00f6ne Aussicht\u201c", "latitude": 51.042072, "longitude": 7.108771, "timestamp": "2025-05-03T03:03:40.740886+00:00Z", "free_bikes": 1, "empty_slots": null, "extra": {"uid": "34475982", "number": "51548", "bike_uids": ["42641"], "virtual": true}}, {"id": "4a670de1ba472cf015f7144c3b6b91a3", "name": "Hermann-L\u00f6ns-Viertel \u2013 Willy-Brandt-Stra\u00dfe", "latitude": 50.988793, "longitude": 7.104658, "timestamp": "2025-05-03T03:03:40.741236+00:00Z", "free_bikes": 1, "empty_slots": null, "extra": {"uid": "227530225", "number": "51566", "bike_uids": ["532026"], "virtual": false}}, {"id": "51172f7a61916a6c023a81e75c976301", "name": "Burscheid Dierath", "latitude": 51.086006, "longitude": 7.081659, "timestamp": "2025-05-03T03:03:40.740873+00:00Z", "free_bikes": 0, "empty_slots": null, "extra": {"uid": "32137535", "number": "51546", "bike_uids": [], "virtual": true}}, {"id": "5ba14ef94d0d3e6d5233e0bf2b63a910", "name": "Wermelskirchen Dh\u00fcnn", "latitude": 51.109194, "longitude": 7.256972, "timestamp": "2025-05-03T03:03:40.740812+00:00Z", "free_bikes": 1, "empty_slots": null, "extra": {"uid": "32136019", "number": "51541", "bike_uids": ["532009"], "virtual": true}}, {"id": "5f4aa3bc72918ff5c5435f5557f9f9e1", "name": "Bergisch Gladbach Refrath", "latitude": 50.958251, "longitude": 7.114554, "timestamp": "2025-05-03T03:03:40.740446+00:00Z", "free_bikes": 0, "empty_slots": null, "extra": {"uid": "32134165", "number": "51545", "bike_uids": [], "virtual": true}}, {"id": "6376c0d6c39b5ea4e8e5bc448105f2a0", "name": "Leichlingen Bahnhof", "latitude": 51.107139, "longitude": 7.005667, "timestamp": "2025-05-03T03:03:40.740291+00:00Z", "free_bikes": 5, "empty_slots": 3, "extra": {"uid": "30240121", "number": "51525", "slots": 8, "bike_uids": ["42703", "42681", "42654", "42620", "532043"], "virtual": false}}, {"id": "6653d643240fa2d0d18b00ebe76e6f3d", "name": "Overath Heiligenhaus", "latitude": 50.938861, "longitude": 7.254917, "timestamp": "2025-05-03T03:03:40.740761+00:00Z", "free_bikes": 0, "empty_slots": null, "extra": {"uid": "32135599", "number": "51535", "bike_uids": [], "virtual": true}}, {"id": "69bc32bf4c8f7af5c2707a9e8577ed3e", "name": "Paffrath \u2013 H\u00f6ffenstra\u00dfe", "latitude": 51.000606, "longitude": 7.100396, "timestamp": "2025-05-03T03:03:40.741182+00:00Z", "free_bikes": 6, "empty_slots": null, "extra": {"uid": "227529638", "number": "51564", "bike_uids": ["42684", "42645", "42644", "42712", "532046", "532018"], "virtual": false}}, {"id": "6d3e2b08d8303f1a8675756ded68b00f", "name": "K\u00fcrten Rathaus", "latitude": 51.052444, "longitude": 7.266639, "timestamp": "2025-05-03T03:03:40.740270+00:00Z", "free_bikes": 0, "empty_slots": 8, "extra": {"uid": "30239678", "number": "51529", "slots": 8, "bike_uids": [], "virtual": false}}, {"id": "6dcb995d3bc1ff55618a49e2b7ed7c3a", "name": "Bergisch Gladbach Technologie-Park", "latitude": 50.959278, "longitude": 7.184889, "timestamp": "2025-05-03T03:03:40.740474+00:00Z", "free_bikes": 0, "empty_slots": null, "extra": {"uid": "32134268", "number": "51549", "bike_uids": [], "virtual": true}}, {"id": "6e4b5ab940f4b0f9eb437bd325650087", "name": "Haltestelle Eich", "latitude": 51.13686, "longitude": 7.210078, "timestamp": "2025-05-03T03:03:40.741427+00:00Z", "free_bikes": 0, "empty_slots": null, "extra": {"uid": "476557884", "number": "51580", "bike_uids": [], "virtual": false}}, {"id": "76192b4974dbdf66659b1c50bc08d6cc", "name": "Burscheid Raiffeisenplatz", "latitude": 51.102417, "longitude": 7.155694, "timestamp": "2025-05-03T03:03:40.740241+00:00Z", "free_bikes": 4, "empty_slots": 4, "extra": {"uid": "30239622", "number": "51526", "slots": 8, "bike_uids": ["42639", "42601", "530782", "530777"], "virtual": false}}, {"id": "7a8d41893afd9365b5ff4b9fa155ac71", "name": "Kippekausen \u2013 Burgplatz", "latitude": 50.957607, "longitude": 7.126275, "timestamp": "2025-05-03T03:03:40.741290+00:00Z", "free_bikes": 0, "empty_slots": null, "extra": {"uid": "227530780", "number": "51568", "bike_uids": [], "virtual": false}}, {"id": "7e9f2d746af7ec5ab8d5c1f7fbd74b66", "name": "Lehmbach Wendeplatz Bergische Strasse", "latitude": 50.929, "longitude": 7.197056, "timestamp": "2025-05-03T03:03:40.740947+00:00Z", "free_bikes": 3, "empty_slots": null, "extra": {"uid": "49442475", "number": "51543", "bike_uids": ["42691", "42608", "532007"], "virtual": true}}, {"id": "8953e751d14182e70c5c60c091a0be5a", "name": "Bergisch Gladbach Schildgen", "latitude": 51.014399, "longitude": 7.0816, "timestamp": "2025-05-03T03:03:40.740461+00:00Z", "free_bikes": 0, "empty_slots": null, "extra": {"uid": "32134225", "number": "51539", "bike_uids": [], "virtual": true}}, {"id": "8d5508feb023944cba873efb4e4a60ac", "name": "K\u00fcrten Bechen", "latitude": 51.040278, "longitude": 7.209833, "timestamp": "2025-05-03T03:03:40.740486+00:00Z", "free_bikes": 1, "empty_slots": null, "extra": {"uid": "32134665", "number": "51538", "bike_uids": ["42603"], "virtual": true}}, {"id": "9ea9c8af356b80a33609669421be94c3", "name": "Odenthal Neschen", "latitude": 51.050778, "longitude": 7.174833, "timestamp": "2025-05-03T03:03:40.740713+00:00Z", "free_bikes": 2, "empty_slots": null, "extra": {"uid": "32135453", "number": "51552", "bike_uids": ["532049", "532011"], "virtual": true}}, {"id": "a6e08f6c60d533fd74da9aa0a8efbf5e", "name": "Bockenberg", "latitude": 50.95729, "longitude": 7.18924, "timestamp": "2025-05-03T03:03:40.741348+00:00Z", "free_bikes": 0, "empty_slots": null, "extra": {"uid": "372368300", "number": "51573", "bike_uids": [], "virtual": true}}, {"id": "aadf709e6d56647b5a8e18404541d182", "name": "Bergisches - (H) Br\u00fcck Mauspfad 1", "latitude": 50.948867, "longitude": 7.079144, "timestamp": "2025-05-03T03:03:40.741306+00:00Z", "free_bikes": 0, "empty_slots": null, "extra": {"uid": "256607869", "number": "51571", "bike_uids": [], "virtual": false}}, {"id": "b01c42c2df733dd4b4546580977e80e2", "name": "Odenthal Blecher", "latitude": 51.058917, "longitude": 7.122056, "timestamp": "2025-05-03T03:03:40.740542+00:00Z", "free_bikes": 0, "empty_slots": null, "extra": {"uid": "32135341", "number": "51551", "bike_uids": [], "virtual": true}}, {"id": "b1ada0dd289db48609aac579d95c5d1e", "name": "Hebborn \u2013 Engelsgut", "latitude": 51.002421, "longitude": 7.125144, "timestamp": "2025-05-03T03:03:40.741168+00:00Z", "free_bikes": 0, "empty_slots": null, "extra": {"uid": "227517874", "number": "51563", "bike_uids": [], "virtual": false}}, {"id": "b4347117567bae12088705149be6851f", "name": "Odenthal Altenberg ", "latitude": 51.052734, "longitude": 7.129503, "timestamp": "2025-05-03T03:03:40.740382+00:00Z", "free_bikes": 3, "empty_slots": 6, "extra": {"uid": "30282698", "number": "51530", "slots": 8, "bike_uids": ["42709", "42658", "532045"], "virtual": false}}, {"id": "b52ae1dd09e47c3fadaf7a9e8f265c42", "name": "Schlebusch Stadtbahn Bergisches", "latitude": 51.019269, "longitude": 7.044286, "timestamp": "2025-05-03T03:03:40.741012+00:00Z", "free_bikes": 0, "empty_slots": null, "extra": {"uid": "114157532", "number": "51555", "bike_uids": [], "virtual": false}}, {"id": "b8d562132bcf8c8b4da4c444db4b813f", "name": "Schlebusch Post Bergisches", "latitude": 51.036263, "longitude": 7.052273, "timestamp": "2025-05-03T03:03:40.740996+00:00Z", "free_bikes": 0, "empty_slots": null, "extra": {"uid": "114157087", "number": "51554", "bike_uids": [], "virtual": false}}, {"id": "b8f8222ca1d73949c84ab593b1e0a733", "name": "R\u00f6srath Bahnhof", "latitude": 50.900797, "longitude": 7.182677, "timestamp": "2025-05-03T03:03:40.740341+00:00Z", "free_bikes": 4, "empty_slots": 9, "extra": {"uid": "30240394", "number": "51527", "slots": 12, "bike_uids": ["42632", "42631", "42711", "532028"], "virtual": false}}, {"id": "bb1a67137266c3ef83ff69c4043a2f47", "name": "Bergisch Gladbach Herrenstrunden", "latitude": 51.007556, "longitude": 7.181611, "timestamp": "2025-05-03T03:03:40.740427+00:00Z", "free_bikes": 1, "empty_slots": null, "extra": {"uid": "32134117", "number": "51547", "bike_uids": ["532035"], "virtual": true}}, {"id": "bcdc7cfe28befc782a7effa87d421ba7", "name": "Leichlingen Busbahnhof", "latitude": 51.105236, "longitude": 7.015886, "timestamp": "2025-05-03T03:03:40.740507+00:00Z", "free_bikes": 1, "empty_slots": null, "extra": {"uid": "32134828", "number": "51540", "bike_uids": ["42670"], "virtual": true}}, {"id": "beffcb154e84303c4ca9e4bb1c1ca496", "name": "Pohlhausen Wendeschleife", "latitude": 51.147675, "longitude": 7.185895, "timestamp": "2025-05-03T03:03:40.741044+00:00Z", "free_bikes": 5, "empty_slots": null, "extra": {"uid": "149650839", "number": "51557", "bike_uids": ["42667", "42636", "42630", "42629", "532021"], "virtual": true}}, {"id": "c3658515943c1ffe95449ce50dff9d9d", "name": "Kreishaus - Bergisch Gladbach", "latitude": 50.976852, "longitude": 7.143302, "timestamp": "2025-05-03T03:03:40.741383+00:00Z", "free_bikes": 0, "empty_slots": null, "extra": {"uid": "375458753", "number": "51575", "bike_uids": [], "virtual": true}}, {"id": "cad5a27dbf136bc91d0d008af4c7c597", "name": "Much - Rathaus Bergisches", "latitude": 50.906081, "longitude": 7.402543, "timestamp": "2025-05-03T03:03:40.741114+00:00Z", "free_bikes": 0, "empty_slots": 8, "extra": {"uid": "149966141", "number": "51560", "slots": 8, "bike_uids": [], "virtual": false}}, {"id": "d2d80f40ba3abb9866b31ed8c1105a84", "name": "Leichlingen - Witzhelden", "latitude": 51.117556, "longitude": 7.110639, "timestamp": "2025-05-03T03:03:40.740525+00:00Z", "free_bikes": 0, "empty_slots": 6, "extra": {"uid": "32134890", "number": "51521", "slots": 8, "bike_uids": [], "virtual": false}}, {"id": "d3aed381257ea87af5dd9e4f8ca04fb2", "name": "(H) K\u00f6nigsforst - Bergisches E-Bike", "latitude": 50.919989, "longitude": 7.097028, "timestamp": "2025-05-03T03:03:40.741133+00:00Z", "free_bikes": 0, "empty_slots": null, "extra": {"uid": "149974334", "number": "51561", "bike_uids": [], "virtual": false}}, {"id": "d7bd2cc14e28e118e3d1b9703b08cbb7", "name": "Bensberg U/Busbahnhof", "latitude": 50.963972, "longitude": 7.161333, "timestamp": "2025-05-03T03:03:40.740204+00:00Z", "free_bikes": 1, "empty_slots": 12, "extra": {"uid": "30239595", "number": "51524", "slots": 12, "bike_uids": ["532027"], "virtual": false}}, {"id": "d7da7b9469b6a12eda53996128eaa59d", "name": "Overath Bahnhof", "latitude": 50.932625, "longitude": 7.288045, "timestamp": "2025-05-03T03:03:40.740316+00:00Z", "free_bikes": 8, "empty_slots": 5, "extra": {"uid": "30240231", "number": "51531", "slots": 12, "bike_uids": ["42708", "42683", "42680", "42656", "42618", "42615", "530778", "532038"], "virtual": false}}, {"id": "dbadfc4224816d3922170c20c8385f0b", "name": "Bergisches - (H) Thielenbruch", "latitude": 50.978007, "longitude": 7.086504, "timestamp": "2025-05-03T03:03:40.741319+00:00Z", "free_bikes": 0, "empty_slots": null, "extra": {"uid": "256609255", "number": "51572", "bike_uids": [], "virtual": false}}, {"id": "ec75dfc20f4a95dce245d481ed4b2c05", "name": "Burscheid Rathaus", "latitude": 51.082717, "longitude": 7.12009, "timestamp": "2025-05-03T03:03:40.740905+00:00Z", "free_bikes": 3, "empty_slots": 2, "extra": {"uid": "41026989", "number": "51542", "slots": 6, "bike_uids": ["42677", "42611", "532032"], "virtual": false}}, {"id": "ee4d1ac5e6fcb9a48ec4201588bd1810", "name": "RVK", "latitude": 51.130166, "longitude": 7.20101, "timestamp": "2025-05-03T03:03:40.741396+00:00Z", "free_bikes": 0, "empty_slots": null, "extra": {"uid": "471945393", "number": "51578", "bike_uids": [], "virtual": false}}, {"id": "f2046db4997cb63f69fe29253651f1bc", "name": " Duckterath - Damaschkestr", "latitude": 50.984904, "longitude": 7.1022, "timestamp": "2025-05-03T03:03:40.741333+00:00Z", "free_bikes": 0, "empty_slots": null, "extra": {"uid": "372361428", "number": "51533", "bike_uids": [], "virtual": false}}, {"id": "f7063392c4a6d7c1f56c2d2efd29b917", "name": " Untereschbach - Overath", "latitude": 50.948575, "longitude": 7.215542, "timestamp": "2025-05-03T03:03:40.741361+00:00Z", "free_bikes": 4, "empty_slots": null, "extra": {"uid": "372373866", "number": "51574", "bike_uids": ["42650", "42647", "42606", "532034"], "virtual": true}}, {"id": "f77e468b75c37ec2c9957b53ed04125a", "name": "Bergisch Gladbach - S/Busbahnhof ", "latitude": 50.990333, "longitude": 7.12325, "timestamp": "2025-05-03T03:03:40.740173+00:00Z", "free_bikes": 0, "empty_slots": 11, "extra": {"uid": "29654533", "number": "51522", "slots": 12, "bike_uids": [], "virtual": false}}, {"id": "f952f681540d71d1425e07adbd6e6a2b", "name": "Hand \u2013 August-Kierspel-Stra\u00dfe", "latitude": 50.99224, "longitude": 7.096039, "timestamp": "2025-05-03T03:03:40.741212+00:00Z", "free_bikes": 0, "empty_slots": null, "extra": {"uid": "227530014", "number": "51565", "bike_uids": [], "virtual": false}}, {"id": "ff45329b7d30db2c8dc219de42e16d84", "name": "Lohmar - Stadthaus  - Bergisches E-Bike", "latitude": 50.842668, "longitude": 7.214885, "timestamp": "2025-05-03T03:03:40.741072+00:00Z", "free_bikes": 0, "empty_slots": 8, "extra": {"uid": "149965176", "number": "51558", "slots": 8, "bike_uids": [], "virtual": false}}]}